odoo/addons/account_cutoff_base/README.rst
odoo/addons/account_cutoff_base/__init__.py
odoo/addons/account_cutoff_base/__manifest__.py
odoo/addons/account_cutoff_base/i18n/account_cutoff_base.pot
odoo/addons/account_cutoff_base/i18n/am.po
odoo/addons/account_cutoff_base/i18n/ar.po
odoo/addons/account_cutoff_base/i18n/bg.po
odoo/addons/account_cutoff_base/i18n/bs.po
odoo/addons/account_cutoff_base/i18n/ca.po
odoo/addons/account_cutoff_base/i18n/cs.po
odoo/addons/account_cutoff_base/i18n/da.po
odoo/addons/account_cutoff_base/i18n/de.po
odoo/addons/account_cutoff_base/i18n/el_GR.po
odoo/addons/account_cutoff_base/i18n/en_GB.po
odoo/addons/account_cutoff_base/i18n/es.po
odoo/addons/account_cutoff_base/i18n/es_AR.po
odoo/addons/account_cutoff_base/i18n/es_CL.po
odoo/addons/account_cutoff_base/i18n/es_CO.po
odoo/addons/account_cutoff_base/i18n/es_CR.po
odoo/addons/account_cutoff_base/i18n/es_DO.po
odoo/addons/account_cutoff_base/i18n/es_EC.po
odoo/addons/account_cutoff_base/i18n/es_ES.po
odoo/addons/account_cutoff_base/i18n/es_MX.po
odoo/addons/account_cutoff_base/i18n/es_PE.po
odoo/addons/account_cutoff_base/i18n/es_PY.po
odoo/addons/account_cutoff_base/i18n/es_VE.po
odoo/addons/account_cutoff_base/i18n/et.po
odoo/addons/account_cutoff_base/i18n/eu.po
odoo/addons/account_cutoff_base/i18n/fa.po
odoo/addons/account_cutoff_base/i18n/fi.po
odoo/addons/account_cutoff_base/i18n/fr.po
odoo/addons/account_cutoff_base/i18n/fr_CH.po
odoo/addons/account_cutoff_base/i18n/fr_FR.po
odoo/addons/account_cutoff_base/i18n/gl.po
odoo/addons/account_cutoff_base/i18n/gl_ES.po
odoo/addons/account_cutoff_base/i18n/he.po
odoo/addons/account_cutoff_base/i18n/hr.po
odoo/addons/account_cutoff_base/i18n/hr_HR.po
odoo/addons/account_cutoff_base/i18n/hu.po
odoo/addons/account_cutoff_base/i18n/id.po
odoo/addons/account_cutoff_base/i18n/it.po
odoo/addons/account_cutoff_base/i18n/ja.po
odoo/addons/account_cutoff_base/i18n/ko.po
odoo/addons/account_cutoff_base/i18n/lt.po
odoo12_addon_account_cutoff_base-12.0.1.1.0.dist-info/METADATA
odoo12_addon_account_cutoff_base-12.0.1.1.0.dist-info/WHEEL
odoo12_addon_account_cutoff_base-12.0.1.1.0.dist-info/top_level.txt
odoo12_addon_account_cutoff_base-12.0.1.1.0.dist-info/RECORD
